README.md
setup.py
drug_learning/__init__.py
drug_learning.egg-info/PKG-INFO
drug_learning.egg-info/SOURCES.txt
drug_learning.egg-info/dependency_links.txt
drug_learning.egg-info/requires.txt
drug_learning.egg-info/top_level.txt
drug_learning/3D/__init__.py
drug_learning/simulation/__init__.py
drug_learning/two_dimensions/__init__.py
drug_learning/two_dimensions/main_fingerprints.py
drug_learning/two_dimensions/sdf_to_input.py
drug_learning/two_dimensions/Errors/__init__.py
drug_learning/two_dimensions/Errors/errors.py
drug_learning/two_dimensions/Input/__init__.py
drug_learning/two_dimensions/Input/applicability_domain.py
drug_learning/two_dimensions/Input/base_class.py
drug_learning/two_dimensions/Input/fingerprints.py
drug_learning/two_dimensions/Output/__init__.py
drug_learning/two_dimensions/Output/output.py
tests/__init__.py
tests/conftest.py
tests/test_AD.py
tests/test_fingerprints.py